microservice_core_bakhodirs_cut.py
microservice_core_bakhodirs_cut-0.0.5.dist-info/WHEEL
microservice_core_bakhodirs_cut-0.0.5.dist-info/METADATA
microservice_core_bakhodirs_cut-0.0.5.dist-info/RECORD
